kpu/__init__.py
kpu/_native/__init__.py
kpu/_native/_native.cp39-win_amd64.pyd
kpu/compiler.py
kpu/datasets.py
kpu/dfx_emitter.py
kpu/fusion.py
kpu/fx_converter.py
kpu/graph.py
kpu/inference.py
kpu/memory_planner.py
kpu/model.py
kpu/model_loader.py
kpu/models/__init__.py
kpu/models/mobilenet.py
kpu/models/simple.py
kpu/models/squeezenet.py
kpu/ops.py
kpu/quantization.py
kpu/runtime.py
kpu/tensor.py
kpu/torch_backend.py
stillwater_kpu-0.8.0.dist-info/METADATA
stillwater_kpu-0.8.0.dist-info/WHEEL
stillwater_kpu-0.8.0.dist-info/RECORD
