Metadata-Version: 2.2
Name: stillwater-kpu
Version: 0.8.0
Summary: KPU (Knowledge Processing Unit) Simulator Python API with native C++ backend
Keywords: kpu,simulator,neural-network,accelerator,compiler,hardware-simulation
Author-Email: "Stillwater Supercomputing, Inc." <info@stillwater-sc.com>
License: Apache-2.0
Classifier: Development Status :: 4 - Beta
Classifier: Intended Audience :: Developers
Classifier: Intended Audience :: Science/Research
Classifier: Operating System :: POSIX :: Linux
Classifier: Operating System :: MacOS
Classifier: Operating System :: Microsoft :: Windows
Classifier: Programming Language :: Python :: 3
Classifier: Programming Language :: Python :: 3.9
Classifier: Programming Language :: Python :: 3.10
Classifier: Programming Language :: Python :: 3.11
Classifier: Programming Language :: Python :: 3.12
Classifier: Programming Language :: C++
Classifier: Topic :: Scientific/Engineering :: Artificial Intelligence
Classifier: Topic :: Software Development :: Compilers
Project-URL: Homepage, https://github.com/stillwater-sc/kpu-sim
Project-URL: Documentation, https://github.com/stillwater-sc/kpu-sim/tree/main/docs
Project-URL: Repository, https://github.com/stillwater-sc/kpu-sim
Project-URL: Issues, https://github.com/stillwater-sc/kpu-sim/issues
Project-URL: Changelog, https://github.com/stillwater-sc/kpu-sim/blob/main/python/CHANGELOG.md
Requires-Python: >=3.9
Requires-Dist: numpy>=1.20.0
Provides-Extra: dev
Requires-Dist: pytest>=7.0.0; extra == "dev"
Requires-Dist: pytest-cov>=4.0.0; extra == "dev"
Requires-Dist: build; extra == "dev"
Requires-Dist: twine; extra == "dev"
Provides-Extra: torch
Requires-Dist: torch>=2.0.0; extra == "torch"
Provides-Extra: bfloat16
Requires-Dist: ml_dtypes>=0.3.0; extra == "bfloat16"
Provides-Extra: all
Requires-Dist: stillwater-kpu[bfloat16,dev,torch]; extra == "all"
